sida/__init__.py
sida/cs228/__init__.py
sida/cs228/show.py
sida/cs228/standardize.py
sida/slackbot/__init__.py
sida/slackbot/bot.py
sida-0.1.3.dist-info/METADATA
sida-0.1.3.dist-info/WHEEL
sida-0.1.3.dist-info/top_level.txt
sida-0.1.3.dist-info/RECORD
