Metadata-Version: 2.1
Name: sida
Version: 0.1.3
Summary: My personal helper
Home-page: https://github.com/liusida/sida
Author: Sida Liu
Author-email: learner.sida.liu@gmail.com
License: UNKNOWN
Platform: UNKNOWN
Classifier: Programming Language :: Python :: 3
Classifier: Programming Language :: Python :: 3.7
Classifier: License :: OSI Approved :: MIT License
Classifier: Operating System :: OS Independent
Requires-Dist: numpy
Requires-Dist: matplotlib
Requires-Dist: websocket-client
